hdx/database/__init__.py
hdx/database/_version.py
hdx/database/database.py
hdx/database/dburi.py
hdx/database/no_timezone.py
hdx/database/postgresql.py
hdx/database/utils.py
hdx/database/views.py
hdx/database/with_timezone.py
hdx_python_database-1.3.8.dist-info/METADATA
hdx_python_database-1.3.8.dist-info/WHEEL
hdx_python_database-1.3.8.dist-info/licenses/LICENSE
hdx_python_database-1.3.8.dist-info/RECORD
