Metadata-Version: 2.4
Name: hdx-python-database
Version: 1.3.8
Summary: HDX Python database utilities
Project-URL: Homepage, https://github.com/OCHA-DAP/hdx-python-database
Author-email: Michael Rans <rans@email.com>
License: MIT
License-File: LICENSE
Keywords: HDX,database,postgresql
Classifier: Development Status :: 5 - Production/Stable
Classifier: Intended Audience :: Developers
Classifier: License :: OSI Approved :: MIT License
Classifier: Natural Language :: English
Classifier: Operating System :: MacOS
Classifier: Operating System :: Microsoft :: Windows
Classifier: Operating System :: POSIX :: Linux
Classifier: Operating System :: Unix
Classifier: Programming Language :: Python
Classifier: Programming Language :: Python :: 3
Classifier: Programming Language :: Python :: 3 :: Only
Classifier: Programming Language :: Python :: 3.8
Classifier: Programming Language :: Python :: 3.9
Classifier: Programming Language :: Python :: 3.10
Classifier: Programming Language :: Python :: 3.11
Classifier: Programming Language :: Python :: 3.12
Classifier: Topic :: Software Development :: Libraries :: Python Modules
Requires-Python: >=3.10
Requires-Dist: sqlalchemy>=2
Provides-Extra: dev
Requires-Dist: pre-commit; extra == 'dev'
Provides-Extra: docs
Requires-Dist: mkapi; extra == 'docs'
Provides-Extra: postgresql
Requires-Dist: psycopg[binary]; extra == 'postgresql'
Provides-Extra: sshtunnel
Requires-Dist: sshtunnel; extra == 'sshtunnel'
Provides-Extra: test
Requires-Dist: psycopg[binary]; extra == 'test'
Requires-Dist: pytest; extra == 'test'
Requires-Dist: pytest-cov; extra == 'test'
Requires-Dist: sshtunnel; extra == 'test'
